strings_utils/__init__.py
strings_utils/string.py
strings_utils-0.0.2.dist-info/METADATA
strings_utils-0.0.2.dist-info/WHEEL
strings_utils-0.0.2.dist-info/top_level.txt
strings_utils-0.0.2.dist-info/RECORD
