Metadata-Version: 2.1
Name: strings-utils
Version: 0.0.2
Summary: Utilities for multi-language projects
Home-page: https://github.com/Princic-1837592/strings-utils
Author: Andrea Princic
Author-email: princic.1837592@studenti.uniroma1.it
License: UNKNOWN
Platform: UNKNOWN
Requires-Python: >=3.6
